<?xml version="1.0" encoding="utf-8" ?>
<dwsync>
<file name="splash.png" server="112.175.184.74" local="132118606181171665" remote="132121729200000000" Dst="0" />
<file name="bg01.mp3" server="112.175.184.74" local="132107535501262074" remote="132121729200000000" Dst="0" />
<file name="birdcall3.wav" server="112.175.184.74" local="130607501920000000" remote="132121729200000000" Dst="0" />
<file name="birdcall1.wav" server="112.175.184.74" local="130607470940000000" remote="132121729200000000" Dst="0" />
<file name="birdcall2.wav" server="112.175.184.74" local="130607501640000000" remote="132121729200000000" Dst="0" />
<file name="die_bird.wav" server="112.175.184.74" local="130607501900000000" remote="132121729200000000" Dst="0" />
<file name="go.wav" server="112.175.184.74" local="131699373115078024" remote="132121729200000000" Dst="0" />
<file name="ready.wav" server="112.175.184.74" local="131699372951268762" remote="132121729200000000" Dst="0" />
<file name="timeup.wav" server="112.175.184.74" local="131699373875215666" remote="132121729200000000" Dst="0" />
<file name="btn_ready_off.png" server="112.175.184.74" local="132118604060346269" remote="132121729200000000" Dst="0" />
<file name="btn_ready_on.png" server="112.175.184.74" local="132118603792689170" remote="132121729200000000" Dst="0" />
<file name="btn_start_off.png" server="112.175.184.74" local="132118603218937727" remote="132121729200000000" Dst="0" />
<file name="btn_start_on.png" server="112.175.184.74" local="132118602248501825" remote="132121729200000000" Dst="0" />
<file name="go.png" server="112.175.184.74" local="132097908997108459" remote="132121729200000000" Dst="0" />
<file name="ready.png" server="112.175.184.74" local="132097908804153269" remote="132121729200000000" Dst="0" />
<file name="bap.png" server="112.175.184.74" local="132107440882245504" remote="132121729200000000" Dst="0" />
<file name="bee.png" server="112.175.184.74" local="132107430472400670" remote="132121729200000000" Dst="0" />
<file name="boo.png" server="112.175.184.74" local="132107409795593186" remote="132121729200000000" Dst="0" />
<file name="ground.png" server="112.175.184.74" local="132110154698932556" remote="132121729200000000" Dst="0" />
<file name="sky.png" server="112.175.184.74" local="132107574952617325" remote="132121729200000000" Dst="0" />
<file name="font.fnt" server="112.175.184.74" local="131575381960000000" remote="132121729200000000" Dst="0" />
<file name="font.png" server="112.175.184.74" local="131575381960000000" remote="132121729200000000" Dst="0" />
<file name="point_icon.png" server="112.175.184.74" local="132121379474599089" remote="132121729200000000" Dst="0" />
</dwsync>